LICENSE
README.md
setup.py
bancor_simulator/__init__.py
bancor_simulator/main.py
bancor_simulator.egg-info/PKG-INFO
bancor_simulator.egg-info/SOURCES.txt
bancor_simulator.egg-info/dependency_links.txt
bancor_simulator.egg-info/entry_points.txt
bancor_simulator.egg-info/requires.txt
bancor_simulator.egg-info/top_level.txt
bancor_simulator/tests/__init__.py
bancor_simulator/tests/data/scenarios.json
bancor_simulator/v3/__init__.py
bancor_simulator/v3/cli_utils.py
bancor_simulator/v3/logger.py
bancor_simulator/v3/simulation/__init__.py
bancor_simulator/v3/simulation/agents.py
bancor_simulator/v3/simulation/batch_run.py
bancor_simulator/v3/simulation/constants.py
bancor_simulator/v3/simulation/model.py
bancor_simulator/v3/simulation/random_walk.py
bancor_simulator/v3/simulation/run.py
bancor_simulator/v3/simulation/server.py
bancor_simulator/v3/simulation/utils.py
bancor_simulator/v3/spec/__init__.py
bancor_simulator/v3/spec/actions.py
bancor_simulator/v3/spec/emulation.py
bancor_simulator/v3/spec/network.py
bancor_simulator/v3/spec/rewards.py
bancor_simulator/v3/spec/state.py
bancor_simulator/v3/spec/utils.py