Metadata-Version: 2.1
Name: bancor-simulator
Version: 1.1.0
Summary: Bancor v3 python spec and simulation library. This is an open-source python package developed by the Bancor Research Team.It is meant to assist in the design, testing, and validating of Bancor v3 behavior.
Home-page: https://github.com/bancorprotocol/simulator-v3
Author: Bancor Network
Author-email: mike@bancor.network
License: UNKNOWN
Platform: UNKNOWN
Provides-Extra: complete
License-File: LICENSE
